FMAPOKE/__init__.py
FMAPOKE/random_pokemon.py
FMAPOKE-1.0.0.dist-info/METADATA
FMAPOKE-1.0.0.dist-info/WHEEL
FMAPOKE-1.0.0.dist-info/top_level.txt
FMAPOKE-1.0.0.dist-info/RECORD
